aws_ecs_gcp_workload_identity/__init__.py
aws_ecs_gcp_workload_identity/aws_instance_credentials.py
aws_ecs_gcp_workload_identity_federation-0.0.1.dist-info/LICENSE
aws_ecs_gcp_workload_identity_federation-0.0.1.dist-info/METADATA
aws_ecs_gcp_workload_identity_federation-0.0.1.dist-info/WHEEL
aws_ecs_gcp_workload_identity_federation-0.0.1.dist-info/top_level.txt
aws_ecs_gcp_workload_identity_federation-0.0.1.dist-info/RECORD
