Metadata-Version: 2.1
Name: aws-ecs-gcp-workload-identity-federation
Version: 0.0.1
Summary: aws-ecs-gcp-workload-identity-federation: This package solves Amazon ECS credential issues with AWS and GCP Workload Identity Federation.
Home-page: https://github.com/ohsawa0515/aws-ecs-gcp-workload-identity-federation
Author: Shuichi Ohsawa
Author-email: ohsawa0515@gmail.com
Maintainer: Shuichi Ohsawa
Maintainer-email: ohsawa0515@gmail.com
License: MIT
Download-URL: https://github.com/ohsawa0515/aws-ecs-gcp-workload-identity-federation
Platform: UNKNOWN
Classifier: License :: OSI Approved :: MIT License
Classifier: Programming Language :: Python :: 3
Classifier: Programming Language :: Python :: 3.6
Classifier: Programming Language :: Python :: 3.7
Classifier: Programming Language :: Python :: 3.8
Classifier: Programming Language :: Python :: 3.9
Classifier: Programming Language :: Python :: 3 :: Only
Requires-Python: >=3.6
Requires-Dist: requests
